cluster_ping/__init__.py
cluster_ping/cluster_ping.py
cluster_ping-0.1.1.dist-info/LICENSE
cluster_ping-0.1.1.dist-info/METADATA
cluster_ping-0.1.1.dist-info/WHEEL
cluster_ping-0.1.1.dist-info/entry_points.txt
cluster_ping-0.1.1.dist-info/RECORD
