Metadata-Version: 2.1
Name: cluster-ping
Version: 0.1.1
Summary: Simple script to ping given clusters using a given kube config. Results are save to a yaml file in /tmp
Home-page: https://github.com/Boomatang/cluster_ping
License: MIT
Author: Jim Fitzpatrick
Author-email: jfitzpat@redhat.com
Requires-Python: >=3.9,<4.0
Classifier: Intended Audience :: Developers
Classifier: License :: OSI Approved :: MIT License
Classifier: Programming Language :: Python :: 3
Classifier: Programming Language :: Python :: 3.9
Classifier: Programming Language :: Python :: 3.10
Classifier: Programming Language :: Python :: 3.11
Classifier: Programming Language :: Python :: 3.12
Requires-Dist: psutil (>=6.0.0,<7.0.0)
Requires-Dist: pyyaml (>=6.0.2,<7.0.0)
Project-URL: Repository, https://github.com/Boomatang/cluster_ping
